pippack/__init__.py
pippack/main.py
pippack-0.1.3.dist-info/licenses/LICENSE
pippack-0.1.3.dist-info/METADATA
pippack-0.1.3.dist-info/WHEEL
pippack-0.1.3.dist-info/entry_points.txt
pippack-0.1.3.dist-info/top_level.txt
pippack-0.1.3.dist-info/RECORD
