Metadata-Version: 2.4
Name: pippack
Version: 0.1.3
Summary: A tool to list installed pip packages excluding dependencies
Home-page: 
Author: Varinder Singh
Classifier: Programming Language :: Python :: 3
Classifier: License :: OSI Approved :: MIT License
Classifier: Operating System :: OS Independent
Requires-Python: >=3.6
License-File: LICENSE
Dynamic: author
Dynamic: classifier
Dynamic: description
Dynamic: description-content-type
Dynamic: license-file
Dynamic: requires-python
Dynamic: summary
